portfolio_tracker/__init__.py
portfolio_tracker/manager.py
portfolio_tracker/price_repo.py
portfolio_tracker/utils.py
portfolio_tracker-0.2.0.2.dist-info/METADATA
portfolio_tracker-0.2.0.2.dist-info/WHEEL
portfolio_tracker-0.2.0.2.dist-info/top_level.txt
portfolio_tracker-0.2.0.2.dist-info/RECORD
