Metadata-Version: 2.1
Name: portfolio-tracker
Version: 0.2.0.2
Summary: A portfolio tracker library, that allows to track a portfolio of stocks and their performance.
Author: Poli Luca
Requires-Python: >=3.10
Requires-Dist: pandas
Requires-Dist: yfinance
Requires-Dist: numpy
Requires-Dist: pandas-market-calendars
Requires-Dist: openpyxl
